[
  {
    "id": 1,
    "name": "Folder A",
    "size": 3453,
    "createdAt": "2020-01-01T00:00:00.000Z",
    "modifiedAt": null,
    "deletedAt": null,
    "color": null,
    "isFavorite": true,
    "isDeleted": false
  },
  {
    "id": 2,
    "name": "Folder B",
    "size": 657,
    "createdAt": "2020-01-01T00:00:00.000Z",
    "modifiedAt": null,
    "deletedAt": null,
    "color": null,
    "isFavorite": false,
    "isDeleted": false
  },
  {
    "id": 3,
    "name": "Folder C",
    "size": 56754,
    "createdAt": "2020-01-01T00:00:00.000Z",
    "modifiedAt": null,
    "deletedAt": null,
    "color": null,
    "isFavorite": true,
    "isDeleted": false
  },
  {
    "id": 4,
    "name": "Folder D",
    "size": 4575,
    "createdAt": "2020-01-01T00:00:00.000Z",
    "modifiedAt": null,
    "deletedAt": null,
    "color": null,
    "isFavorite": false,
    "isDeleted": false
  },
  {
    "id": 5,
    "name": "Folder E",
    "size": 0,
    "createdAt": "2020-01-01T00:00:00.000Z",
    "modifiedAt": null,
    "deletedAt": null,
    "color": null,
    "isFavorite": false,
    "isDeleted": false
  }
]